mondeja_bump.py
mondeja_bump-0.2.3.dist-info/entry_points.txt
mondeja_bump-0.2.3.dist-info/WHEEL
mondeja_bump-0.2.3.dist-info/METADATA
mondeja_bump-0.2.3.dist-info/RECORD
