Metadata-Version: 2.1
Name: mondeja-bump
Version: 0.2.3
Summary: Just bump semantic version.
License: BSD-3-Clause
Author: Álvaro Mondéjar Rubio
Author-email: mondejar1994@gmail.com
Requires-Python: >=3.7,<4.0
Classifier: License :: OSI Approved :: BSD License
Classifier: Programming Language :: Python :: 3
Classifier: Programming Language :: Python :: 3.7
Classifier: Programming Language :: Python :: 3.8
Classifier: Programming Language :: Python :: 3.9
Classifier: Programming Language :: Python :: 3.10
Requires-Dist: tomli; python_version < "3.11"
